multisarge.py
multisarge-0.1.0.dist-info/DESCRIPTION.rst
multisarge-0.1.0.dist-info/METADATA
multisarge-0.1.0.dist-info/RECORD
multisarge-0.1.0.dist-info/WHEEL
multisarge-0.1.0.dist-info/metadata.json
multisarge-0.1.0.dist-info/top_level.txt
