Metadata-Version: 2.0
Name: multisarge
Version: 0.1.0
Summary: Multiprocessing Task Runner Using Sarge
Home-page: https://github.com/fireforge/multisarge
Author: David A. Salter
Author-email: david.salter.12@gmail.com
License: MIT
Platform: UNKNOWN
Requires-Dist: sarge
